var peace = {
"type": "FeatureCollection",
"crs": { "type": "name", "properties": { "name": "urn:ogc:def:crs:OGC:1.3:CRS84" } },
"features": [
{ "type": "Feature", "properties": { "id": 1, "descrip": "peace college" }, "geometry": { "type": "Point", "coordinates": [ -78.637582, 35.789288 ] } }
]
}